astro/__init__.py
astro/cache.py
astro/cli.py
astro/cmd/__init__.py
astro/cmd/moon.py
astro/cmd/twilight.py
astro/cmd/whereis.py
astro/geo.py
astro/lib.py
astro_cli-0.1.3.dist-info/entry_points.txt
astro_cli-0.1.3.dist-info/WHEEL
astro_cli-0.1.3.dist-info/METADATA
astro_cli-0.1.3.dist-info/RECORD
